rain_api/__init__.py
rain_api/cli.py
rain_api/core/__init__.py
rain_api/core/config.py
rain_api/core/pages.py
rain_api/core/templates.py
tests/__init__.py
tests/test_rain_api.py
rain_api-0.1.2.dist-info/LICENSE
rain_api-0.1.2.dist-info/METADATA
rain_api-0.1.2.dist-info/WHEEL
rain_api-0.1.2.dist-info/entry_points.txt
rain_api-0.1.2.dist-info/top_level.txt
rain_api-0.1.2.dist-info/RECORD
