Metadata-Version: 2.1
Name: rain-api
Version: 0.1.2
Summary: # Rain Api
Requires-Dist: atomicwrites (==1.3.0)
Requires-Dist: attrs (==19.3.0)
Requires-Dist: autopep8 (==1.5.2)
Requires-Dist: certifi (==2020.4.5.1)
Requires-Dist: chardet (==3.0.4)
Requires-Dist: click (==7.1.1)
Requires-Dist: colorama (==0.4.3)
Requires-Dist: entrypoints (==0.3)
Requires-Dist: flake8 (==3.7.9)
Requires-Dist: idna (==2.9)
Requires-Dist: mccabe (==0.6.1)
Requires-Dist: more-itertools (==8.2.0)
Requires-Dist: packaging (==20.3)
Requires-Dist: Pillow (==7.1.1)
Requires-Dist: pluggy (==0.13.1)
Requires-Dist: py (==1.8.1)
Requires-Dist: pycodestyle (==2.5.0)
Requires-Dist: pyflakes (==2.1.1)
Requires-Dist: PyMySQL (==0.9.3)
Requires-Dist: pyparsing (==2.4.7)
Requires-Dist: pytest (==5.4.1)
Requires-Dist: requests (==2.23.0)
Requires-Dist: six (==1.14.0)
Requires-Dist: urllib3 (==1.25.9)
Requires-Dist: wcwidth (==0.1.9)
